[
  {
    "year": 2024,
    "list": [
      {
        "month": "Jan",
        "date": "27",
        "day": "Mon",
        "timestamp": 1746158904
      },
      {
        "month": "Feb",
        "date": "25",
        "day": "Tue",
        "timestamp": 1746148904
      },
      {
        "month": "Mar",
        "date": "21",
        "day": "Wed",
        "timestamp": 1746138904
      },
      {
        "month": "Apr",
        "date": "18",
        "day": "Thu",
        "timestamp": 1746128904
      },
      {
        "month": "May",
        "date": "15",
        "day": "Fri",
        "timestamp": 1746111904
      },
      {
        "month": "Jun",
        "date": "11",
        "day": "Sat",
        "timestamp": 1746112904
      },
      {
        "month": "July",
        "date": "7",
        "day": "Sun",
        "timestamp": 1746113904
      },
      {
        "month": "Aug",
        "date": "2",
        "day": "Mon",
        "timestamp": 1746114904
      },
      {
        "month": "Sep",
        "date": "26",
        "day": "Tue",
        "timestamp": 1746115904
      },
      {
        "month": "Oct",
        "date": "24",
        "day": "Wed",
        "timestamp": 1746116904
      },
      {
        "month": "Nov",
        "date": "13",
        "day": "Thu",
        "timestamp": 1746117904
      },
      {
        "month": "Dec",
        "date": "2",
        "day": "Fri",
        "timestamp": 1746118904
      }
    ]
  },
  {
    "year": 2025,
    "list": [
      {
        "month": "Jan",
        "date": "27",
        "day": "Mon",
        "timestamp": 1746158904
      },
      {
        "month": "Feb",
        "date": "25",
        "day": "Tue",
        "timestamp": 1746148904
      },
      {
        "month": "Mar",
        "date": "21",
        "day": "Wed",
        "timestamp": 1746138904
      },
      {
        "month": "Apr",
        "date": "18",
        "day": "Thu",
        "timestamp": 1746128904
      },
      {
        "month": "May",
        "date": "15",
        "day": "Fri",
        "timestamp": 1746111904
      },
      {
        "month": "Jun",
        "date": "11",
        "day": "Sat",
        "timestamp": 1746112904
      },
      {
        "month": "July",
        "date": "7",
        "day": "Sun",
        "timestamp": 1746113904
      },
      {
        "month": "Aug",
        "date": "2",
        "day": "Mon",
        "timestamp": 1746114904
      },
      {
        "month": "Sep",
        "date": "26",
        "day": "Tue",
        "timestamp": 1746115904
      },
      {
        "month": "Oct",
        "date": "24",
        "day": "Wed",
        "timestamp": 1746116904
      },
      {
        "month": "Nov",
        "date": "13",
        "day": "Thu",
        "timestamp": 1746117904
      },
      {
        "month": "Dec",
        "date": "2",
        "day": "Fri",
        "timestamp": 1746118904
      }
    ]
  }
]
